Metadata-Version: 2.1
Name: VSTAR
Version: 0.1.0
Summary: Auto refresh for Latex in VS-code
Home-page: https://github.com/dragonoverlord3000/VSTAR.git
Author: Dragonoverlord3000
Author-email: hugomn2002@gmail.com
License: UNKNOWN
Platform: UNKNOWN
Classifier: Development Status :: 1 - Planning
Classifier: Intended Audience :: Science/Research
Classifier: Operating System :: Microsoft :: Windows
Classifier: Programming Language :: Python :: 3.8
